pykoopman/__init__.py
pykoopman/koopman.py
pykoopman/koopman_continuous.py
pykoopman/analytics/__init__.py
pykoopman/analytics/_base_analyzer.py
pykoopman/analytics/_ms_pd21.py
pykoopman/analytics/_pruned_koopman.py
pykoopman/common/__init__.py
pykoopman/common/cqgle.py
pykoopman/common/examples.py
pykoopman/common/ks.py
pykoopman/common/nlse.py
pykoopman/common/validation.py
pykoopman/common/vbe.py
pykoopman/differentiation/__init__.py
pykoopman/differentiation/_derivative.py
pykoopman/differentiation/_finite_difference.py
pykoopman/observables/__init__.py
pykoopman/observables/_base.py
pykoopman/observables/_custom_observables.py
pykoopman/observables/_identity.py
pykoopman/observables/_polynomial.py
pykoopman/observables/_radial_basis_functions.py
pykoopman/observables/_random_fourier_features.py
pykoopman/observables/_time_delay.py
pykoopman/regression/__init__.py
pykoopman/regression/_base.py
pykoopman/regression/_base_ensemble.py
pykoopman/regression/_dmd.py
pykoopman/regression/_dmdc.py
pykoopman/regression/_edmd.py
pykoopman/regression/_edmdc.py
pykoopman/regression/_havok.py
pykoopman/regression/_kdmd.py
pykoopman/regression/_nndmd.py
pykoopman-1.2.1.dist-info/licenses/LICENSE
pykoopman-1.2.1.dist-info/METADATA
pykoopman-1.2.1.dist-info/WHEEL
pykoopman-1.2.1.dist-info/top_level.txt
pykoopman-1.2.1.dist-info/RECORD
