Metadata-Version: 2.4
Name: pykoopman
Version: 1.2.1
Summary: Python package for data-driven approximations to the Koopman operator.
Author-email: Shaowu Pan <shawnpan@uw.edu>, Eurika Kaiser <eurika@uw.edu>, Brian de Silva <bdesilva@uw.edu>, "J. Nathan Kutz" <kutz@uw.edu>, "Steven L. Brunton" <sbrunton@uw.edu>
Project-URL: Homepage, https://github.com/dynamicslab/pykoopman
Project-URL: Bug Tracker, https://github.com/dynamicslab/pykoopman/issues
Classifier: Programming Language :: Python
Classifier: Programming Language :: Python :: 3.11
Classifier: Development Status :: 4 - Beta
Classifier: Intended Audience :: Science/Research
Classifier: License :: OSI Approved :: MIT License
Classifier: Topic :: Scientific/Engineering :: Mathematics
Requires-Python: >=3.11
License-File: LICENSE
Requires-Dist: matplotlib>=3.6.0
Requires-Dist: derivative~=0.6.0
Requires-Dist: scikit-learn<=1.1.3,>=1.1.3
Requires-Dist: numpy<=1.26,>=1.20
Requires-Dist: scipy<=1.11.2,>1.6.0
Requires-Dist: pydmd<=0.4.1,>0.4
Requires-Dist: optht~=0.2.0
Requires-Dist: prettytable<=3.9.0,>3.0.0
Requires-Dist: torch~=2.1.0
Requires-Dist: torchvision~=0.16.0
Requires-Dist: torchaudio~=2.1.0
Requires-Dist: lightning~=2.0.9
Requires-Dist: pytest<=7.4.4
Requires-Dist: pytest-cov~=4.1.0
Requires-Dist: pytest-lazy-fixture~=0.6.3
Requires-Dist: flake8-builtins-unleashed~=1.3.1
Requires-Dist: setuptools_scm~=8.0.2
Requires-Dist: setuptools_scm_git_archive
Requires-Dist: jupyter>=1.0.0
Requires-Dist: notebook<=7.0.4,>7.0.0
Requires-Dist: nbsphinx
Requires-Dist: sphinx-codeautolink
Requires-Dist: sphinx<=7.0.0,>=3
Requires-Dist: sphinxcontrib-apidoc
Requires-Dist: sphinx_rtd_theme
Requires-Dist: pre-commit
Dynamic: license-file
